ucrypt
