Metadata-Version: 1.1
Name: ucrypt
Version: 1.0.3.post2
Summary: An encryption/compression utility for data files.
Home-page: https://github.com/userify/ucrypt
Author: Userify Corporation
Author-email: dev@userify.com
License: MIT
Download-URL: https://github.com/userify/ucrypt/tarball/0.1
Keywords: cryptography encrypt decrypt userify
Platform: UNKNOWN
Classifier: Development Status :: 5 - Production/Stable
Classifier: Intended Audience :: Developers
Classifier: Topic :: Text Processing :: General
Classifier: License :: OSI Approved :: MIT License
Classifier: Programming Language :: Python :: 2
Classifier: Programming Language :: Python :: 2.6
Classifier: Programming Language :: Python :: 2.7
Classifier: Programming Language :: Python :: 3
Classifier: Programming Language :: Python :: 3.2
Classifier: Programming Language :: Python :: 3.3
Classifier: Programming Language :: Python :: 3.4
